{"name":"Cuisine","identifier":"RGVRSY65SO","description":null,"slotTypeValues":[{"synonyms":null,"sampleValue":{"value":"Japanese"}},{"synonyms":null,"sampleValue":{"value":"Chinese"}},{"synonyms":null,"sampleValue":{"value":"Indian"}},{"synonyms":null,"sampleValue":{"value":"Italian"}},{"synonyms":null,"sampleValue":{"value":"Mexican"}},{"synonyms":null,"sampleValue":{"value":"American"}}],"parentSlotTypeSignature":null,"valueSelectionSetting":{"resolutionStrategy":"ORIGINAL_VALUE","advancedRecognitionSetting":null,"regexFilter":null}}